{
	"header" : 
	{
		"DuplicatedCodeFinder-mode" : "full",
		"FaultHunterPython-mode" : "inactive",
		"LIM2Metrics-mode" : "limited",
		"LIM2Patterns-mode" : "full",
		"MetricHunter-mode" : "full",
		"Pylint2Graph-mode" : "inactive",
		"UserDefinedMetrics-mode" : "inactive",
		"asg" : "python"
	},
	"nodes" : 
	[
		{
			"attributes" : 
			[
				{
					"context" : "attribute",
					"name" : "Name",
					"type" : "string",
					"value" : "<System>"
				},
				{
					"context" : "attribute",
					"name" : "LongName",
					"type" : "string",
					"value" : "<System>"
				},
				{
					"context" : "metric",
					"name" : "CCL",
					"type" : "int",
					"value" : 20
				},
				{
					"context" : "metric",
					"name" : "CCO",
					"type" : "int",
					"value" : 453
				},
				{
					"context" : "metric",
					"name" : "CEE",
					"type" : "float",
					"value" : 3920.86669921875
				},
				{
					"context" : "metric",
					"name" : "CI",
					"type" : "int",
					"value" : 49
				},
				{
					"context" : "metric",
					"name" : "LDC",
					"type" : "int",
					"value" : 1564
				},
				{
					"context" : "metric",
					"name" : "LLDC",
					"type" : "int",
					"value" : 1233
				},
				{
					"context" : "metric",
					"name" : "CC",
					"type" : "float",
					"value" : 0.1276928186416626
				},
				{
					"context" : "metric",
					"name" : "CLLC",
					"type" : "float",
					"value" : 0.096403442323207855
				},
				{
					"context" : "metric",
					"name" : "CLC",
					"type" : "float",
					"value" : 0.093423329293727875
				},
				{
					"context" : "metric",
					"name" : "NCR",
					"type" : "float",
					"value" : 0.33666667342185974
				},
				{
					"context" : "metric",
					"name" : "CR",
					"type" : "float",
					"value" : 3.1002607345581055
				},
				{
					"context" : "metric",
					"name" : "CEG",
					"type" : "float",
					"value" : 35.809246063232422
				},
				{
					"context" : "metric",
					"name" : "TLLOC",
					"type" : "int",
					"value" : 12790
				},
				{
					"context" : "metric",
					"name" : "TLOC",
					"type" : "int",
					"value" : 16741
				},
				{
					"context" : "metric",
					"name" : "TNCL",
					"type" : "int",
					"value" : 62
				},
				{
					"context" : "metric",
					"name" : "TNFI",
					"type" : "int",
					"value" : 91
				},
				{
					"context" : "metric",
					"name" : "TNM",
					"type" : "int",
					"value" : 634
				},
				{
					"context" : "metric",
					"name" : "TNOS",
					"type" : "int",
					"value" : 6131
				},
				{
					"context" : "metric",
					"name" : "TNPKG",
					"type" : "int",
					"value" : 30
				},
				{
					"context" : "metric",
					"name" : "TCLOC",
					"type" : "int",
					"value" : 4381
				},
				{
					"context" : "metric",
					"name" : "TNDI",
					"type" : "int",
					"value" : 34
				},
				{
					"context" : "metric",
					"name" : "WarningBlocker",
					"type" : "int",
					"value" : 0
				},
				{
					"context" : "metric",
					"name" : "WarningCritical",
					"type" : "int",
					"value" : 0
				},
				{
					"context" : "metric",
					"name" : "WarningMajor",
					"type" : "int",
					"value" : 0
				},
				{
					"context" : "metric",
					"name" : "WarningMinor",
					"type" : "int",
					"value" : 0
				},
				{
					"context" : "metric",
					"name" : "WarningInfo",
					"type" : "int",
					"value" : 0
				}
			],
			"name" : "L102",
			"type" : "Component"
		}
	]
}